AUTHORS.md
LICENSE
README.md
setup.cfg
setup.py
fuzzycorr/__init__.py
fuzzycorr/correlation_factory.py
fuzzycorr/strict_orderings.py
fuzzycorr/t_norms.py
fuzzycorr/utils.py
fuzzycorr.egg-info/PKG-INFO
fuzzycorr.egg-info/SOURCES.txt
fuzzycorr.egg-info/dependency_links.txt
fuzzycorr.egg-info/requires.txt
fuzzycorr.egg-info/top_level.txt