Metadata-Version: 2.1
Name: fuzzycorr
Version: 0.1.1
Summary: A numpy implementation of Robust Rank Correlation Coefficients.
Home-page: https://github.com/mikulatomas/fuzzycorr
Author: Tomáš Mikula
Author-email: mail@tomasmikula.cz
License: MIT license
Keywords: fuzzycorr correlation fuzzy
Platform: UNKNOWN
Classifier: Development Status :: 2 - Pre-Alpha
Classifier: Intended Audience :: Science/Research
Classifier: License :: OSI Approved :: MIT License
Classifier: Natural Language :: English
Classifier: Programming Language :: Python :: 3
Classifier: Programming Language :: Python :: 3.7
Classifier: Programming Language :: Python :: 3.8
Classifier: Programming Language :: Python :: 3.9
Requires-Python: >=3.7
Provides-Extra: test
License-File: LICENSE
License-File: AUTHORS.md
